LICENSE
README.md
setup.py
ml4vision/__init__.py
ml4vision/cli.py
ml4vision/cli_functions.py
ml4vision/cli_options.py
ml4vision/client.py
ml4vision/ml/__init__.py
ml4vision/ml/datasets/__init__.py
ml4vision/ml/datasets/dataset.py
ml4vision/ml/utils/image_utils.py
ml4vision/utils/__init__.py
ml4vision/utils/colormap.py
ml4vision/utils/mask_utils.py
ml4vision/utils/rle_cython.c
ml4vision/utils/rle_cython.pyx
ml4vision/utils/yolov5.py
ml4vision_py.egg-info/PKG-INFO
ml4vision_py.egg-info/SOURCES.txt
ml4vision_py.egg-info/dependency_links.txt
ml4vision_py.egg-info/entry_points.txt
ml4vision_py.egg-info/requires.txt
ml4vision_py.egg-info/top_level.txt