Metadata-Version: 2.1
Name: ml4vision-py
Version: 0.1.10
Summary: Python sdk and cli for ml4vision
Home-page: https://github.com/ml4vision/ml4vision-py
Author: ml4vision
Author-email: info@ml4vision.com
Classifier: Programming Language :: Python :: 3
Classifier: License :: OSI Approved :: MIT License
Requires-Python: >=3.6
Provides-Extra: ml
License-File: LICENSE
